Metadata-Version: 1.1
Name: knowledgelab
Version: 0.0.1
Summary: Knowledge Repo integration for JupyterLab
Home-page: https://github.com/timkpaine/knowledgelab
Author: Tim Paine
Author-email: t.paine154@gmail.com
License: LGPL
Download-URL: https://github.com/timkpaine/knowledgelab/archive/v0.0.1.tar.gz
Keywords: analytics jupyter
Platform: UNKNOWN
Classifier: Development Status :: 3 - Alpha
Classifier: Programming Language :: Python :: 3
Classifier: Programming Language :: Python :: 3.3
Classifier: Programming Language :: Python :: 3.4
Classifier: Programming Language :: Python :: 3.5
